llama_index/packs/query_understanding_agent/__init__.py
llama_index/packs/query_understanding_agent/base.py
llama_index/packs/query_understanding_agent/step.py
llama_index_packs_query_understanding_agent-0.3.1.dist-info/METADATA
llama_index_packs_query_understanding_agent-0.3.1.dist-info/WHEEL
llama_index_packs_query_understanding_agent-0.3.1.dist-info/licenses/LICENSE
llama_index_packs_query_understanding_agent-0.3.1.dist-info/RECORD
