Metadata-Version: 2.4
Name: llama-index-packs-query-understanding-agent
Version: 0.3.1
Summary: llama-index packs query understanding agent integration
Author-email: Sasha Sheng <hackgoofer@gmail.com>
License-Expression: MIT
License-File: LICENSE
Requires-Python: <4.0,>=3.9
Requires-Dist: llama-index-core<0.13,>=0.12.0
Requires-Dist: llama-index-llms-openai<0.5,>=0.4.0
